kozhindev_clearml_wrapper/__init__.py
kozhindev_clearml_wrapper/utils.py
kozhindev_clearml_wrapper-0.0.2.dist-info/licenses/LICENCE
kozhindev_clearml_wrapper-0.0.2.dist-info/METADATA
kozhindev_clearml_wrapper-0.0.2.dist-info/WHEEL
kozhindev_clearml_wrapper-0.0.2.dist-info/top_level.txt
kozhindev_clearml_wrapper-0.0.2.dist-info/RECORD
