Metadata-Version: 2.4
Name: kozhindev_clearml_wrapper
Version: 0.0.2
Summary: Wrapper over clearml, developed by ML team of KozhinDev company
Author: YVoskanyan
Author-email: yuvoskanyan@team.kozhin.dev
Keywords: clearml-wrapper clearml wrapper
Classifier: Programming Language :: Python :: 3.12
Classifier: License :: OSI Approved :: MIT License
Classifier: Operating System :: OS Independent
Requires-Python: >=3.9
License-File: LICENCE
Requires-Dist: clearml>=2.0.2
Dynamic: author
Dynamic: author-email
Dynamic: classifier
Dynamic: description
Dynamic: description-content-type
Dynamic: keywords
Dynamic: license-file
Dynamic: requires-dist
Dynamic: requires-python
Dynamic: summary
